frz_jupyterlab_sublime/__init__.py
frz_jupyterlab_sublime/_version.py
frz_jupyterlab_sublime/labextension/build_log.json
frz_jupyterlab_sublime/labextension/package.json
frz_jupyterlab_sublime/labextension/static/lib_index_js.0c1f04bc5478a63deab2.js
frz_jupyterlab_sublime/labextension/static/lib_index_js.0c1f04bc5478a63deab2.js.map
frz_jupyterlab_sublime/labextension/static/remoteEntry.c0855ff4a22af8f8f7f0.js
frz_jupyterlab_sublime/labextension/static/remoteEntry.c0855ff4a22af8f8f7f0.js.map
frz_jupyterlab_sublime/labextension/static/style.js
frz_jupyterlab_sublime/labextension/static/style_index_js.e6a917ef7178460a8b49.js
frz_jupyterlab_sublime/labextension/static/style_index_js.e6a917ef7178460a8b49.js.map
frz_jupyterlab_sublime/labextension/static/vendors-node_modules_css-loader_dist_runtime_api_js-node_modules_css-loader_dist_runtime_cssW-72eba1.e92c5f9163357e12acaf.js
frz_jupyterlab_sublime/labextension/static/vendors-node_modules_css-loader_dist_runtime_api_js-node_modules_css-loader_dist_runtime_cssW-72eba1.e92c5f9163357e12acaf.js.map
frz_jupyterlab_sublime-0.1.4.data/data/share/jupyter/labextensions/jupyterlab_sublime/build_log.json
frz_jupyterlab_sublime-0.1.4.data/data/share/jupyter/labextensions/jupyterlab_sublime/install.json
frz_jupyterlab_sublime-0.1.4.data/data/share/jupyter/labextensions/jupyterlab_sublime/package.json
frz_jupyterlab_sublime-0.1.4.data/data/share/jupyter/labextensions/jupyterlab_sublime/static/lib_index_js.0c1f04bc5478a63deab2.js
frz_jupyterlab_sublime-0.1.4.data/data/share/jupyter/labextensions/jupyterlab_sublime/static/lib_index_js.0c1f04bc5478a63deab2.js.map
frz_jupyterlab_sublime-0.1.4.data/data/share/jupyter/labextensions/jupyterlab_sublime/static/remoteEntry.c0855ff4a22af8f8f7f0.js
frz_jupyterlab_sublime-0.1.4.data/data/share/jupyter/labextensions/jupyterlab_sublime/static/remoteEntry.c0855ff4a22af8f8f7f0.js.map
frz_jupyterlab_sublime-0.1.4.data/data/share/jupyter/labextensions/jupyterlab_sublime/static/style.js
frz_jupyterlab_sublime-0.1.4.dist-info/LICENSE
frz_jupyterlab_sublime-0.1.4.dist-info/METADATA
frz_jupyterlab_sublime-0.1.4.dist-info/WHEEL
frz_jupyterlab_sublime-0.1.4.dist-info/top_level.txt
frz_jupyterlab_sublime-0.1.4.dist-info/RECORD
